{
    "length": 60,
    "data": [
        {
            "Substantially Performed": "2011-05-09",
            "Date certificate signed:": "2011-05-19",
            "Name of Owner": "Nisbet Lodge",
            "Address of Owner": "740 Pape Ave., Toronto, ON M4K 3S7",
            "Name of Contractor": "Brook Restoration Ltd.",
            "Address of Contractor": "11 Kelfield Street, Toronto, ON",
            "Consultant": "Read Jones Christoffersen Ltd.",
            "Consultant Address": "144 Front St. West, Suite 500, Toronto, ON M5J 2L7",
            "Publicaton Date": "2011-06-01",
            "Address": "740 Pape Ave., Toronto,  Ontario ",
            "Location": "Toronto, Ontario",
            "Project": "2010 Localized Exterior Wall Rehabilitation",
            "Certificate Number": "B2F71E44-0A73-4C44-842F-02D739E5C096"
        },
        {
            "Substantially Performed": "2011-04-18",
            "Date certificate signed:": "2011-04-19",
            "Name of Owner": "Destaron Property Management Inc.",
            "Address of Owner": "Destaron Property Management Inc., 510 Maple Avenue, Suite 7",
            "Name of Contractor": "Brook Restoration Ltd.",
            "Address of Contractor": "11 Kelfield Street, Toronto, ON M9W 5A1",
            "Consultant": "Ontech Building Consultants Inc.",
            "Consultant Address": "136 Cedric Avenue, Toronto, ON M6C 3X8",
            "Publicaton Date": "2011-04-29",
            "Address": "21 & 41 Pioneer Drive, Kitchener, Ontario c/o Destaron Property Management Inc., 510 Maple Avenue, Suite 705, Burlington, Ontario L5N 1H2 ",
            "Location": "Kitchener,  Ontario",
            "Project": "Building Roof Replacement",
            "Certificate Number": "6128280C-0141-4FAD-835C-909CF29C963E"
        },
        {
            "Substantially Performed": "2011-04-18",
            "Date certificate signed:": "2011-04-19",
            "Name of Owner": "Destaron Property Management Inc.",
            "Address of Owner": "Destaron Property Management Inc., 510 Maple Avenue, Suite 7",
            "Name of Contractor": "Brook Restoration Ltd.",
            "Address of Contractor": "11 Kelfield Street, Toronto, ON M9W 5A1",
            "Consultant": "Ontech Building Consultants Inc.",
            "Consultant Address": "136 Cedric Avenue, Toronto, ON M6C 3X8",
            "Publicaton Date": "2011-04-29",
            "Address": "21 & 41 Pioneer Drive, Kitchener, Ontario c/o Destaron Property Management Inc., 510 Maple Avenue, Suite 705, Burlington, Ontario L5N 1H2 ",
            "Location": "Kitchener,  Ontario",
            "Project": "Restoration of Parking Garage Ramp",
            "Certificate Number": "4F2B7194-6F33-4A44-9C5B-C8B07C6F1EBB"
        },
        {
            "Substantially Performed": "2011-03-31",
            "Date certificate signed:": "2011-04-15",
            "Name of Owner": "Bell Canada",
            "Address of Owner": "Nexacor Realty Management Inc., 20 Hunter Street West, 3rd F",
            "Name of Contractor": "Brook Restoration Ltd.",
            "Address of Contractor": "11 Kelfield Street, Toronto, ON M9W 5A1",
            "Consultant": "GENIVAR Inc.",
            "Consultant Address": "1-367 Woodlawn Road West, Guelph, ON N1H 7K9",
            "Publicaton Date": "2011-04-27",
            "Address": "63 King Street, St. Catharines, Ontario L2R 3H6 ",
            "Location": "St. Catharines",
            "Project": "Installation of Roof Anchors and Building Envelope Repairs",
            "Certificate Number": "AD5C978D-6060-4D56-A5AF-3A0D76EF56D7"
        },
        {
            "Substantially Performed": "2010-11-12",
            "Date certificate signed:": "2010-11-15",
            "Name of Owner": "York Condominium Corporation No. 106",
            "Address of Owner": "c/o Malvern Condominium Property Management, 1850 Albion Roa",
            "Name of Contractor": "Brook Restoration Ltd.",
            "Address of Contractor": "11 Kelfield Street, Toronto, ON M9W 5A1",
            "Consultant": "Brown & Beattie Ltd.",
            "Consultant Address": "556 Edward Avenue, Unit 71, Richmond Hill, ON L4C 9Y5",
            "Publicaton Date": "2011-04-08",
            "Address": " ",
            "Location": "15 La Rose Avenue, Toronto",
            "Project": "Parking Garage Roof Slab Repair",
            "Certificate Number": "7788DAE8-87A0-46D4-A6F1-E8D4DAA10402"
        },
        {
            "Substantially Performed": "2011-03-25",
            "Date certificate signed:": "2011-03-28",
            "Name of Owner": "Hugh Garner Housing Co-operative Inc.",
            "Address of Owner": "550 Ontario Street, Toronto, ON M4X 1X3",
            "Name of Contractor": "Brook Restoration Ltd.",
            "Address of Contractor": "11 Kelfield Street, Toronto, ON M9W 5A1",
            "Consultant": "Read Jones Christoffersen Ltd.",
            "Consultant Address": "144 Front St. West, Suite 500, Toronto, ON M5J 2L7",
            "Publicaton Date": "2011-04-01",
            "Address": "550 Ontario Street, Toronto, Ontario ",
            "Location": "Toronto, Ontario",
            "Project": "Glazing Replacement",
            "Certificate Number": "0B8CF87D-A453-47F5-B603-DFD1CD119862"
        },
        {
            "Substantially Performed": "2011-03-24",
            "Date certificate signed:": "2011-03-28",
            "Name of Owner": "Bread and Roses Co-operative Homes (Kitchener) Inc.",
            "Address of Owner": "307 Queen Street South, Kitchener, ON N2G 4V3",
            "Name of Contractor": "Brook Restoration Limited",
            "Address of Contractor": "11 Kelfield Street, Toronto, ON M9W 5A1",
            "Consultant": "Kleinfeldt Consultants Limited",
            "Consultant Address": "Suite 102, 2400 Meadowpine Blvd., Mississauga, ON L5N 6S2",
            "Publicaton Date": "2011-04-01",
            "Address": "307 Queen Street  South, Kitchener, Ontario ",
            "Location": "City of Kitchener",
            "Project": "Restoration/Upgrade Project",
            "Certificate Number": "C3C71ADC-2A1B-47CC-B43F-7F6B41FE02C3"
        },
        {
            "Substantially Performed": "2011-03-14",
            "Date certificate signed:": "2011-03-18",
            "Name of Owner": "Kawartha Lakes Haliburton Housing Corporation",
            "Address of Owner": "322 Kent Street, Lindsay, ON K9V 4S7",
            "Name of Contractor": "Brook Restoration",
            "Address of Contractor": "11 Kelfield Street, Toronto, ON M9W 5A1",
            "Consultant": "Ronald A. Awde Architect",
            "Consultant Address": "1458 King Street, Bethany, ON L0A 1A0",
            "Publicaton Date": "2011-03-28",
            "Address": "92 Albert  Street, 45 Durham Street, 19 Hamilton Street, 48 St.  Paul Street, 45 St. Patrick Street, Lindsay, Ontario ",
            "Location": "City of Kawartha Lakes",
            "Project": "Washroom Upgrades",
            "Certificate Number": "368663C9-12EE-4202-8947-B16320557021"
        },
        {
            "Date certificate signed:": "2011-02-11",
            "Name of Owner": "York Condominium Corporation #41",
            "Address of Owner": "180 Markham Road, Toronto, ON M1M 2Z9",
            "Name of Contractor": "Brook Restoration Ltd.",
            "Address of Contractor": "11 Kelfield Street, Toronto, ON M9W 5A1",
            "Consultant": "H. Rentsch Associates Ltd.",
            "Consultant Address": "130 Bridgeland Avenue, Suite #211, Toronto, ON M6A 1Z4",
            "Publicaton Date": "2011-02-22",
            "Address": "180 Markham Road, M1M  2Z9, Toronto, Ontario ",
            "Location": "Toronto, Ontario",
            "Project": "Balcony Repairs Waterproofing & New Railings Installation",
            "Certificate Number": "314918F0-2B0C-4852-8F7B-0042A933B65B"
        },
        {
            "Substantially Performed": "2011-01-24",
            "Date certificate signed:": "2011-02-02",
            "Name of Owner": "Callan Property Management Group",
            "Address of Owner": "905-165 Dundas Street West, Mississauga, ON L5B 2N6",
            "Name of Contractor": "Brook Restoration Ltd.",
            "Address of Contractor": "11 Kelfield Street, Toronto, ON M9W 5A1",
            "Consultant": "BEST Consultants Martin Gerskup Architect Inc.",
            "Consultant Address": "15 Melissa Court, Maple, ON",
            "Publicaton Date": "2011-02-11",
            "Address": "165 Dundas Street West, Mississauga,  ON ",
            "Location": "City of Mississauga",
            "Project": "Repair of the Parking Garage",
            "Certificate Number": "3E73BF53-2A2E-44C0-81AB-9C4BA9367098"
        },
        {
            "Substantially Performed": "2011-01-25",
            "Date certificate signed:": "2011-01-25",
            "Name of Owner": "Royal Canadian Military Police",
            "Address of Owner": "345 Harry Walker Parkway, Newmarket, ON L3Y 8P6",
            "Name of Contractor": "Brook Restoration Limited",
            "Address of Contractor": "11 Kelfield Street, Toronto, ON M9W 5A1",
            "Consultant": "Base3 Architect Inc.",
            "Consultant Address": "406-3100 Steeles Avenue West, Vaughan, ON L4K 4R1",
            "Publicaton Date": "2011-02-09",
            "Address": "345 Harry Walker Parkway, Newmarket, Ontario L3Y 8P6 ",
            "Location": "Town of Newmarket",
            "Project": "Cladding Cleaning",
            "Certificate Number": "99E1E1FB-4AEF-4056-A179-87B6788B8636"
        },
        {
            "Substantially Performed": "2010-12-24",
            "Date certificate signed:": "2011-01-11",
            "Name of Owner": "Crown Property Management",
            "Address of Owner": "3080 Yonge Street, Suite 2050, Toronto, ON M4N 3N1",
            "Name of Contractor": "Brook Restoration Ltd.",
            "Address of Contractor": "11 Kelfield Street, Toronto, ON M9W 5A1",
            "Consultant": "Stantec Consulting Ltd.",
            "Consultant Address": "675 Cochrane Drive, Suite 300, Markham, ON L3R 0B8",
            "Publicaton Date": "2011-01-18",
            "Address": "Crown Property Management ",
            "Location": "City of Toronto",
            "Project": "Sealant Replacement Program, South Elevation of 415 Yonge Street, Toronto, ON",
            "Certificate Number": "B108F8F2-45CC-4A7E-8105-16FD49297F32"
        },
        {
            "Substantially Performed": "2010-11-05",
            "Date certificate signed:": "2010-11-05",
            "Name of Owner": "Royalwood Developments Ltd. c/o Briarlane Property Management Inc.",
            "Address of Owner": "85 Spy Court, Suite 100, Markham, ON L3R 4Z4",
            "Name of Contractor": "Brook Restoration",
            "Address of Contractor": "11 Kelfield Street, Toronto, ON M9W 5A1",
            "Consultant": "Davroc & Associates Ltd.",
            "Consultant Address": "2051 Williams Parkway, Unit 21, Brampton, ON L6S 5T4",
            "Publicaton Date": "2011-01-12",
            "Address": "55 Brownlow Ave., Toronto, Ontario ",
            "Location": "City of Toronto",
            "Project": "Parking Garage Rehabilitation",
            "Certificate Number": "43BC137A-D6AB-44EA-B823-851AD2F7E815"
        },
        {
            "Substantially Performed": "2010-10-08",
            "Date certificate signed:": "2010-10-20",
            "Name of Owner": "Regional Municipality of Waterloo",
            "Address of Owner": "150 Frederick Street, Kitchener, ON N2G 4J3",
            "Name of Contractor": "Brook Restoration",
            "Address of Contractor": "11 Kelfield Street, Toronto, ON M9W 5A1",
            "Consultant": "Peter Suwalski, P.Eng., M.Eng. Pretium Engineering Limited",
            "Consultant Address": "320 Woolwich Street South, Breslau, ON N0B 1M0",
            "Publicaton Date": "2011-01-10",
            "Address": "145 Overlea Drive, Kitchener ",
            "Location": "Waterloo Region",
            "Project": "Masonry Repairs and EIFS Installation",
            "Certificate Number": "51DEC37B-CE82-465C-9765-A772BC854AA2"
        },
        {
            "Substantially Performed": "2010-11-24",
            "Date certificate signed:": "2010-12-01",
            "Name of Owner": "Destaron Property Management Ltd.",
            "Address of Owner": "510 Maple Avenue, Suite 705, Burlington, ON L7S 1M5",
            "Name of Contractor": "Brook Restoration Ltd.",
            "Address of Contractor": "11 Kelfield Street, Toronto, ON M9W 5A1",
            "Consultant": "Davroc & Associates Ltd.",
            "Consultant Address": "2051 Williams Parkway East, Unit 21, Brampton, ON L6S 5T4",
            "Publicaton Date": "2010-12-17",
            "Address": "101 Kozlov Street, Barrie, Ontario ",
            "Location": "City of Barrie",
            "Project": "Balcony Rehabilitation",
            "Certificate Number": "51AA717E-6585-4FE0-9E62-E48110829C37"
        },
        {
            "Substantially Performed": "2010-11-04",
            "Date certificate signed:": "2010-11-08",
            "Name of Owner": "Birch Cliff Cooperative Homes Inc.",
            "Address of Owner": "1691 Kingston Road, Unit 1, Toronto, ON M1N 1S6",
            "Name of Contractor": "Brook Restoration Ltd.",
            "Address of Contractor": "11 Kelfield Street, Toronto, ON M9W 5A1",
            "Consultant": "CMS Building Consultants Inc.",
            "Consultant Address": "100 Dynamic Drive, Unit 10, Scarborough, ON M1V 5C4",
            "Publicaton Date": "2010-11-16",
            "Address": "1691 Kingston Road,  Unit 1, Toronto, Ontario M1N 1S6 ",
            "Location": "City of Toronto",
            "Project": "Proposed Brick Masonry Remedial Work",
            "Certificate Number": "433D2391-9AFD-442B-A966-284722714551"
        },
        {
            "Substantially Performed": "2010-11-01",
            "Date certificate signed:": "2010-11-03",
            "Name of Owner": "Northview Meadows Co-operative",
            "Address of Owner": "1252 Pentland Street, Suite 100, Oshawa, ON",
            "Name of Contractor": "Brook Restoration",
            "Address of Contractor": "11 Kelfield Street, Toronto, ON",
            "Consultant": "Enerplan Building Consultants (a division of Synergon Incorporated)",
            "Consultant Address": "69 Judson Street, Toronto, ON M8Z 1A4",
            "Publicaton Date": "2010-11-10",
            "Address": "1252 Pentland Street ",
            "Location": "Oshawa, Ontario",
            "Project": "Roofing Replacement Remedial Work",
            "Certificate Number": "D26A49AE-0FE1-45F5-BF1F-58323CBD7C62"
        },
        {
            "Substantially Performed": "2010-10-29",
            "Date certificate signed:": "2010-11-01",
            "Name of Owner": "David B. Archer Co-operative Inc.",
            "Address of Owner": "158 The Esplanade, Toronto, ON M5A 3T2",
            "Name of Contractor": "Brook Restoration Ltd.",
            "Address of Contractor": "11 Kelfield Street, Toronto, ON M9W 5A1",
            "Consultant": "CMS Building Consultants Inc.",
            "Consultant Address": "100 Dynamic Drive, Unit 10, Scarborough, ON M1V 5C4",
            "Publicaton Date": "2010-11-05",
            "Address": "158 The Esplanade, Toronto, Ontario M5A 3T2 ",
            "Location": "City of Toronto",
            "Project": "Balcony Remedial Work at Apartment Building Suites at 713",
            "Certificate Number": "B5EC5976-5125-4D05-8B13-EDE1E2073877"
        },
        {
            "Substantially Performed": "2010-10-26",
            "Date certificate signed:": "2010-10-26",
            "Name of Owner": "MI Developments Inc.",
            "Address of Owner": "455 Magna Drive, Aurora, ON L4G 7A9",
            "Name of Contractor": "Brook Restoration Ltd.",
            "Address of Contractor": "11 Kelfield Street, Toronto, ON M9W 5A1",
            "Consultant": "Read Jones Christoffersen Ltd.",
            "Consultant Address": "144 Front St. West, Suite 500, Toronto, ON M5J 2L7",
            "Publicaton Date": "2010-11-03",
            "Address": "455 Manga Drive, Aurora, Ontario ",
            "Location": "Aurora, Ontario",
            "Project": "Interior Building Rehabilitation",
            "Certificate Number": "B5911DF0-8B84-445F-AD4B-D522B000EE88"
        },
        {
            "Substantially Performed": "2010-10-18",
            "Date certificate signed:": "2010-10-18",
            "Name of Owner": "Heath Street Housing Co-Operative Inc. c/o Management Office",
            "Address of Owner": "230 & 232 Heath Street West, Toronto, ON M5P 1N8",
            "Name of Contractor": "Brook Restoration Limited",
            "Address of Contractor": "11 Kelfield Street, Toronto, ON M9W 5A1",
            "Consultant": "Davroc & Associates Ltd.",
            "Consultant Address": "2051 Williams Parkway, Unit 21, Brampton, ON L6S 5T4",
            "Publicaton Date": "2010-10-26",
            "Address": "230 & 232 Heath Street West, Toronto, Ontario ",
            "Location": "City of Toronto",
            "Project": "Brick Masonry Repairs",
            "Certificate Number": "62777EDC-AB11-4BA6-B207-1FC74D605CAA"
        },
        {
            "Substantially Performed": "2010-08-31",
            "Date certificate signed:": "2010-10-18",
            "Name of Owner": "Metro Toronto Condominium Corporation No. 1230",
            "Address of Owner": "c/o goldview Property Management Ltd., 51 Toro Road, Suite 2",
            "Name of Contractor": "Brook Restoration Ltd.",
            "Address of Contractor": "11 Kelfield Street, Toronto, ON M9W 5A1",
            "Consultant": "Gillespie Building Consultants Inc.",
            "Consultant Address": "156-3007 Kingston Road, Scarborough, ON M1M 1P1",
            "Publicaton Date": "2010-10-25",
            "Address": "1231 Yonge Street ",
            "Location": "City of Toronto",
            "Project": "Localized Repairs to EIFS System",
            "Certificate Number": "C583105A-6430-4A3D-A243-AC670F547B55"
        },
        {
            "Substantially Performed": "2010-10-13",
            "Date certificate signed:": "2010-10-14",
            "Name of Owner": "Durham Region Non-Profit Housing Corporation",
            "Address of Owner": "28A Albert Street, Oshawa, ON L1H 8S5",
            "Name of Contractor": "Brook Restoration Ltd.",
            "Address of Contractor": "11 Kelfield Street, Toronto, ON M9W 5A1",
            "Consultant": "Enerplan Building Consultants (a division of Synergon Incorporated)",
            "Consultant Address": "69 Judson Street, Toronto, ON M8Z 1A4",
            "Publicaton Date": "2010-10-22",
            "Address": "90 Waller Street, Whitby, Ontario ",
            "Location": "Durham  Region",
            "Project": "Stairwell Cladding Installation",
            "Certificate Number": "64D0D9BA-2BB1-45D6-ADB7-043C87E61667"
        },
        {
            "Substantially Performed": "2010-10-08",
            "Date certificate signed:": "2010-10-14",
            "Name of Owner": "University of Guelph",
            "Address of Owner": "Physical Resources, J.C. Hersey Building #60, Guelph, ON N1G",
            "Name of Contractor": "Brook Restoration Ltd.",
            "Address of Contractor": "11 Kelfield Street, Toronto, ON M9W 5A1",
            "Consultant": "The Walter Fedy Partnership",
            "Consultant Address": "487 Riverbend Drive, Kitchener, ON N2K 3S3",
            "Publicaton Date": "2010-10-22",
            "Address": "University of Guelph, Trent Lane to College Avenue ",
            "Location": "Wellington County",
            "Project": "University of Guelph, Trent Lane to College Avenue Tunnel Restoration",
            "Certificate Number": "48E5CC7C-FB90-4092-8DDA-E19FFAC49EC0"
        },
        {
            "Substantially Performed": "2010-09-16",
            "Date certificate signed:": "2010-10-07",
            "Name of Owner": "Metropolitan Toronto Condominium Corporation 970",
            "Address of Owner": "c/o Management Office, 3311 Kingston Road, Toronto, ON M1M 1",
            "Name of Contractor": "Brook Restoration Ltd.",
            "Address of Contractor": "11 Kelfield Street, Toronto, ON M9W 5A1",
            "Consultant": "BEST Consultants Martin Gerskup Architect Inc.",
            "Consultant Address": "15 Melissa Court, Maple, ON",
            "Publicaton Date": "2010-10-14",
            "Address": "3311 Kingston Road, Toronto,  ON ",
            "Location": "Municipality of Metropolitan Toronto",
            "Project": "Window Replacement Project",
            "Certificate Number": "1A05BF55-2F53-4EC3-B01F-C18172D3119E"
        },
        {
            "Substantially Performed": "2010-09-06",
            "Date certificate signed:": "2010-09-08",
            "Name of Owner": "Peel District School Board",
            "Address of Owner": "933 Central Parkway West, Mississauga, ON L5C 2T9",
            "Name of Contractor": "Brook Restoration",
            "Address of Contractor": "11 Kelfield Street, Toronto, ON M9W 5A1",
            "Consultant": "Halsall Associates Limited",
            "Consultant Address": "3050 Harvester Road, Suite 100, Burlington, ON L7N 3J1",
            "Publicaton Date": "2010-09-14",
            "Address": "35 Ellwood Drive East, Bolton ",
            "Location": "Peel Region",
            "Project": "Foundation wall repairs and waterproofing, courtyard restoration and exterior drainage improvements",
            "Certificate Number": "544472E4-358E-4384-BC2B-5104A0299D67"
        },
        {
            "Substantially Performed": "2010-08-23",
            "Date certificate signed:": "2010-08-27",
            "Name of Owner": "Park Property Management Inc.",
            "Address of Owner": "16 Esna Park Drive, Suite 200, Markham, ON L3R 5X1",
            "Name of Contractor": "Brook Restoration Ltd.",
            "Address of Contractor": "11 Kelfield Street, Toronto, ON M9W 5A1",
            "Consultant": "Ontech Building Consultants Inc.",
            "Consultant Address": "136 Cedric Avenue, Toronto, ON M6C 3X8",
            "Publicaton Date": "2010-09-02",
            "Address": "2797 Battleford Drive, City of Mississauga, Ontario ",
            "Location": "Peel Region",
            "Project": "Exterior Unit Masonry & Sealant Repairs",
            "Certificate Number": "F345A2BE-08FC-4690-BA73-8ACDBD3A53C8"
        },
        {
            "Substantially Performed": "2010-06-30",
            "Date certificate signed:": "2010-07-05",
            "Name of Owner": "York Region Condominium Corporation No. 676",
            "Address of Owner": "400 Beacon Hall, Aurora, ON L4G 3G8",
            "Name of Contractor": "Brook Restoration Ltd.",
            "Address of Contractor": "11 Kelfield Street, Toronto, ON M9W 5A1",
            "Consultant": "IRC BuildingSciences Group Inc.",
            "Consultant Address": "7565 Danbro Crescent, Mississauga, ON L5N 6P9",
            "Publicaton Date": "2010-08-26",
            "Address": "Town of Aurora ",
            "Location": "York Region",
            "Project": "Guard Replacement at Tree Tops Lane",
            "Certificate Number": "E639CB1E-239B-43B9-8C27-F1E340A3F53F"
        },
        {
            "Substantially Performed": "2010-08-03",
            "Date certificate signed:": "2010-08-04",
            "Name of Owner": "Park Property Management Inc.",
            "Address of Owner": "16 Esna Park Drive, Suite 200, Markham, ON L3R 5X1",
            "Name of Contractor": "Brook Restoration Ltd.",
            "Address of Contractor": "11 Kelfield Street, Toronto, ON M9W 5A1",
            "Consultant": "Ontech Building Consultants Inc.",
            "Consultant Address": "136 Cedric Avenue, Toronto, ON M6C 3X8",
            "Publicaton Date": "2010-08-10",
            "Address": "3561 Eglinton Ave. W., Toronto, Ontario ",
            "Location": "Toronto, Ontario",
            "Project": "Window Sealant Repairs",
            "Certificate Number": "424518E0-6DEC-462B-A9A6-814D1B8C42ED"
        },
        {
            "Substantially Performed": "2010-07-26",
            "Date certificate signed:": "2010-07-26",
            "Name of Owner": "Park Property Management Inc.",
            "Address of Owner": "16 Esna Park Drive, Suite 200, Markham, ON L3R 5X1",
            "Name of Contractor": "Brook Restoration Ltd.",
            "Address of Contractor": "11 Kelfield Street, Toronto, ON M9W 5A1",
            "Consultant": "Ontech Building Consultants Inc.",
            "Consultant Address": "136 Cedric Avenue, Toronto, ON M6C 3X8",
            "Publicaton Date": "2010-08-09",
            "Address": "2797 Battleford Drive, City of Mississauga, Ontario ",
            "Location": "Peel Region",
            "Project": "Building Balcony Slab and Railing Repairs",
            "Certificate Number": "2DD0162C-9E29-4468-B745-242B9542B848"
        },
        {
            "Substantially Performed": "2010-07-26",
            "Date certificate signed:": "2010-07-26",
            "Name of Owner": "Destaron Property Management",
            "Address of Owner": "510 Maple Avenue, Suite 705, Burlington, ON L7S 1M4",
            "Name of Contractor": "Brook Restoration Ltd.",
            "Address of Contractor": "11 Kelfield Street, Toronto, ON M9W 5A1",
            "Consultant": "Ontech Building Consultants Inc.",
            "Consultant Address": "136 Cedric Avenue, Toronto, ON M6C 3X8",
            "Publicaton Date": "2010-08-09",
            "Address": "50 Burn Hill Road, Toronto, Ontario ",
            "Location": "Toronto, Ontario",
            "Project": "Waterproofing Restoration & Protection of the Underground Parking Garage Roof Deck",
            "Certificate Number": "6C857DC7-8FD7-4F23-A994-466546219284"
        },
        {
            "Substantially Performed": "2010-07-28",
            "Date certificate signed:": "2010-07-29",
            "Name of Owner": "York Condominium Corporation No. 329",
            "Address of Owner": "c/o Larlyn Property Management Ltd., 315 Renfrew Dr., Suite",
            "Name of Contractor": "Brook Restoration Ltd.",
            "Address of Contractor": "11 Kelfield Street, Toronto, ON M9W 5A1",
            "Consultant": "Brown & Beattie Ltd.",
            "Consultant Address": "556 Edward Avenue, Unit 71, Richmond Hill, ON L4C 9Y5",
            "Publicaton Date": "2010-08-09",
            "Address": " ",
            "Location": "825 Kennedy Road, Toronto",
            "Project": "Wall & Garage Repairs",
            "Certificate Number": "20FF4153-9E53-471F-AB69-5CA7C963E288"
        },
        {
            "Substantially Performed": "2010-06-30",
            "Date certificate signed:": "2010-07-07",
            "Name of Owner": "Metropolitan Toronto Condominium Corporation 970",
            "Address of Owner": "c/o Management Office, 3311 Kingston Road, Toronto, ON M1M 1",
            "Name of Contractor": "Brook Restoration Ltd.",
            "Address of Contractor": "11 Kelfield Street, Toronto, ON M9W 5A1",
            "Consultant": "BEST Consultants Martin Gerskup Architect Inc.",
            "Consultant Address": "15 Melissa Court, Maple, ON",
            "Publicaton Date": "2010-07-15",
            "Address": "3311 Kingston Road, Toronto, ON ",
            "Location": "City of Toronto",
            "Project": "Window Replacement Project",
            "Certificate Number": "85D0D3BF-56AB-468C-B0BE-88720BE53810"
        },
        {
            "Substantially Performed": "2010-03-06",
            "Date certificate signed:": "2010-03-10",
            "Name of Owner": "York Condominium Corporation No. 274",
            "Address of Owner": "York Condominium Corporation No. 274, c/o GPM Property Manag",
            "Name of Contractor": "Brook Restoration Ltd.",
            "Address of Contractor": "11 Kelfield Street, Toronto, ON M9W 5A1",
            "Consultant": "Ontech Building Consultants Inc.",
            "Consultant Address": "136 Cedric Avenue, Toronto, ON M6C 3X8",
            "Publicaton Date": "2010-05-21",
            "Address": "75 Graydon Hall Drive, Toronto, Ontario ",
            "Location": "City of Toronto",
            "Project": "Roof Replacement Program Located at 75 Graydon Hall Drive, Toronto, Ontario",
            "Certificate Number": "72B2633E-79BD-4FED-BB0E-3E2EA3862035"
        },
        {
            "Substantially Performed": "2010-04-26",
            "Date certificate signed:": "2010-05-05",
            "Name of Owner": "Metropolitan Toronto Condominium Corporation No. 1277 c/o RamLand Property Management",
            "Address of Owner": "200 Ronson Drive, Suite 305, Toronto, ON M9W 5Z9",
            "Name of Contractor": "Brook Restoration Ltd.",
            "Address of Contractor": "11 Kelfield Street, Toronto, ON M9W 5A1",
            "Consultant": "Davroc & Associates Ltd.",
            "Consultant Address": "2051 Williams Parkway, Unit 21, Brampton, ON L6S 5T4",
            "Publicaton Date": "2010-05-11",
            "Address": "10 Old Mill Trail, Toronto, Ontario ",
            "Location": "City of Toronto",
            "Project": "Thru-Wall Flashing and Brickwork Repairs",
            "Certificate Number": "30851940-1B89-4C36-AC94-C185A9BF33AA"
        },
        {
            "Substantially Performed": "2010-04-16",
            "Date certificate signed:": "2010-04-20",
            "Name of Owner": "Inter Faith Homes (Centenary) Corporation",
            "Address of Owner": "2877 Ellesmere Road, Toronto, ON M1E 4C1",
            "Name of Contractor": "Brook Restoration Ltd.",
            "Address of Contractor": "11 Kelfield Street, Toronto, ON M9W 5A1",
            "Consultant": "Enerplan Building Consultants (a division of Synergon Incorporated)",
            "Consultant Address": "69 Judson Street, Toronto, ON M8Z 1A4",
            "Publicaton Date": "2010-04-27",
            "Address": "400 Crossland Gate ",
            "Location": "Newmarket, Ontario",
            "Project": "Building Envelope Remedial Work",
            "Certificate Number": "A9E12EDB-C278-4B5E-A7A5-99492F82FE82"
        },
        {
            "Substantially Performed": "2009-12-08",
            "Date certificate signed:": "2009-12-15",
            "Name of Owner": "June Callwood Centre for Women and Families",
            "Address of Owner": "205 Parliament Street, Toronto, ON M5A 2Z4",
            "Name of Contractor": "Brook Restoration Ltd.",
            "Address of Contractor": "11 Kelfield Street, Toronto, ON M9W 5A1",
            "Consultant": "Enerplan Building Consultants (a division of Synergon Incorporated)",
            "Consultant Address": "69 Judson Street, Toronto, ON M8Z 1A4",
            "Publicaton Date": "2010-03-29",
            "Address": "205 Parliament Street ",
            "Location": "Toronto, Ontario",
            "Project": "Building Envelope Remedial Work",
            "Certificate Number": "D1ED7192-4A29-44CB-8060-F5AA5446A67F"
        },
        {
            "Substantially Performed": "2009-06-01",
            "Date certificate signed:": "2009-06-29",
            "Name of Owner": "Park Properties Management Inc.",
            "Address of Owner": "100 Spadina Road, Toronto, ON",
            "Name of Contractor": "Brook Restoration",
            "Address of Contractor": "11 Kelfield Street, Toronto, ON M9W 5A1",
            "Consultant": "Construction Control Inc.",
            "Consultant Address": "70 Haist Avenue, Woodbridge, ON L4L 5V4",
            "Publicaton Date": "2010-03-11",
            "Address": "100 Spadina Road, Toronto, ON ",
            "Location": "City of Toronto",
            "Project": "Replacement of Concrete Forming the Boiler Room Roof Slab",
            "Certificate Number": "56456262-0EAF-4261-8453-50EDE17D2913"
        },
        {
            "Substantially Performed": "2009-11-09",
            "Date certificate signed:": "2009-11-09",
            "Name of Owner": "Park Property Management Inc.",
            "Address of Owner": "16 Esna Park Drive, Suite 200, Markham, ON L3R 5X1",
            "Name of Contractor": "Brook Restoration Ltd.",
            "Address of Contractor": "11 Kelfield Street, Toronto, ON M9W 5A1",
            "Consultant": "Ontech Building Consultants Inc.",
            "Consultant Address": "136 Cedric Avenue, Toronto, ON M6C 3X8",
            "Publicaton Date": "2010-02-08",
            "Address": "53 Thorncliffe Park Drive, Toronto, ON ",
            "Location": "Toronto, ON",
            "Project": "Exterior Unit Masonry and Sealant Repairs",
            "Certificate Number": "2B8C15D0-F1E6-44E3-B181-7E7384686FA2"
        },
        {
            "Substantially Performed": "2009-11-10",
            "Date certificate signed:": "2009-12-17",
            "Name of Owner": "Casmik Property Management",
            "Address of Owner": "50 Pearldale Ave, Toronto",
            "Name of Contractor": "Brook Restoration",
            "Address of Contractor": "11 Kelfield Street, Toronto, ON M9W 5A1",
            "Consultant": "Construction Control Inc.",
            "Consultant Address": "70 Haist Avenue, Woodbridge, ON L4L 5V4",
            "Publicaton Date": "2010-01-29",
            "Address": "50 Pearldale Avenue, Toronto,  ON ",
            "Location": "City of Toronto",
            "Project": "Repair of Balcony and Replacement of Ralling",
            "Certificate Number": "EADC45A2-9154-4326-B369-01E7A0C3367A"
        },
        {
            "Substantially Performed": "2009-12-23",
            "Date certificate signed:": "2010-01-25",
            "Name of Owner": "York Condominium Corporation No. 323",
            "Address of Owner": "Management Office, 50 Quebec Avenue, Toronto, ON M6P 4B4",
            "Name of Contractor": "Brook Restoration Ltd.",
            "Address of Contractor": "11 Kelfield Street, Toronto, ON M9W 5A1",
            "Consultant": "Gillespie Building Consultants Inc.",
            "Consultant Address": "156-3007 Kingston Road, Toronto, ON M1M 1P1",
            "Publicaton Date": "2010-01-28",
            "Address": "50 Quebec Avenue ",
            "Location": "City of Toronto",
            "Project": "Restoration of Concrete Balcony Slabs and Replacement of Balcony Railings",
            "Certificate Number": "D2D9EFEA-9243-4F1A-9FE7-9ED3F4B9F118"
        },
        {
            "Substantially Performed": "2010-01-13",
            "Date certificate signed:": "2010-01-14",
            "Name of Owner": "Redcliff Realty Management Inc. as managers for the Owners",
            "Address of Owner": "40 University Avenue, Toronto, ON M5J 1T1",
            "Name of Contractor": "Brook Restoration Ltd.",
            "Address of Contractor": "11 Kelfield Street, Toronto, ON M9W 5A1",
            "Consultant": "N. Grgas Engineering Inc.",
            "Consultant Address": "8 Cambria Place, King City, ON L7B 1B9",
            "Publicaton Date": "2010-01-21",
            "Address": "111 Gordon Baker Road ",
            "Location": "City of Toronto (North York)",
            "Project": "2009 Podium Deck Repairs",
            "Certificate Number": "F20A13CC-16A1-4182-A678-05962EEC43B0"
        },
        {
            "Substantially Performed": "2009-10-15",
            "Date certificate signed:": "2009-10-21",
            "Name of Owner": "Peel District School Board",
            "Address of Owner": "933 Central Parkway W., Mississauga, ON L5C 2T9",
            "Name of Contractor": "Brook Restoration",
            "Address of Contractor": "11 Kelfield Street, Toronto, ON M9W 5A1",
            "Consultant": "Halsall Associates Limited",
            "Consultant Address": "3050 Harvester Rd., Suite 300, Burlington, ON L7N 3J1",
            "Publicaton Date": "2010-01-19",
            "Address": "2021 Dundas Street West, Mississauga (Erindale Secondary School) ",
            "Location": "Peel Region",
            "Project": "2009 Exterior Cladding Repairs",
            "Certificate Number": "A28AD5DF-5BC2-4D34-8E2B-3FC0F709E8C9"
        },
        {
            "Substantially Performed": "2009-12-21",
            "Date certificate signed:": "2009-12-22",
            "Name of Owner": "H & R Property Management Ltd.",
            "Address of Owner": "3625 Dufferin Street, Suite 409, Downsview, ON M3K 1N4",
            "Name of Contractor": "Brook Restoration Ltd.",
            "Address of Contractor": "11 Kelfield Street, Toronto, ON M9W 5A1",
            "Consultant": "H. Rentsch Associates Ltd.",
            "Consultant Address": "130 Bridgeland Avenue, Suite 211, Toronto, ON M6A 1Z4",
            "Publicaton Date": "2010-01-13",
            "Address": " ",
            "Location": "1407 Royal York Road",
            "Project": "Brick & Shear Wall Repairs & Painting",
            "Certificate Number": "1211F703-11DD-40F7-B5D9-BAA26DA3A504"
        },
        {
            "Substantially Performed": "2009-12-17",
            "Date certificate signed:": "2009-12-21",
            "Name of Owner": "David B Archer Co-operative Inc.",
            "Address of Owner": "158 The Esplanade, Toronto, ON M5A 3T2",
            "Name of Contractor": "Brook Restoration Ltd.",
            "Address of Contractor": "11 Kelfield Street, Toronto, ON M9W 5A1",
            "Consultant": "CMS Building Consultants Inc.",
            "Consultant Address": "100 Dynamic Drive, Unit 10, Scarborough, ON M1V 5C4",
            "Publicaton Date": "2010-01-13",
            "Address": "158 The Esplanade, Toronto,  ON M5A 3T2 ",
            "Location": "City of Toronto",
            "Project": "Balcony Remedial Work at Apartment Building Suites at 707 and 712",
            "Certificate Number": "F9F6D60A-368E-4E8B-80D2-72B50A4B9F92"
        },
        {
            "Substantially Performed": "2009-12-18",
            "Date certificate signed:": "2009-12-22",
            "Name of Owner": "Sunrise Suites Holdings Inc. and 1522950 Ontario Inc. c/o Greenwin Property Management Ltd.",
            "Address of Owner": "1 Valleybrook Drive, Suite 200, North York, ON M3B 2S7",
            "Name of Contractor": "Brook Restoration",
            "Address of Contractor": "11 Kelfield Street, Toronto, ON M9W 5A1",
            "Consultant": "Davroc & Associates Ltd.",
            "Consultant Address": "2051 Williams Parkway, Unit 21, Brampton, ON L6S 5T4",
            "Publicaton Date": "2009-12-30",
            "Address": " ",
            "Location": "1240 Donald Street, Ottawa, ON",
            "Project": "Roof Replacement",
            "Certificate Number": "8B05535B-312C-4ECC-AFEC-78E90B16640C"
        },
        {
            "Substantially Performed": "2009-12-15",
            "Date certificate signed:": "2009-12-15",
            "Name of Owner": "Redcliff Realty Management Inc. as managers for the Owner",
            "Address of Owner": "40 University Avenue, Toronto, ON M5J 1T1",
            "Name of Contractor": "Brook Restoration Ltd.",
            "Address of Contractor": "11 Kelfield Street, Toronto, ON M9W 5A1",
            "Consultant": "N. Grgas Engineering Inc.",
            "Consultant Address": "8 Cambria Place, King City, ON L7B 1B9",
            "Publicaton Date": "2009-12-18",
            "Address": "111 Gordon Baker Road ",
            "Location": "City of Toronto (North York)",
            "Project": "Front Parking Expansion",
            "Certificate Number": "63512173-F432-4EB3-8CCC-AA68C0216894"
        },
        {
            "Substantially Performed": "2009-12-04",
            "Date certificate signed:": "2009-12-07",
            "Name of Owner": "York Condominium Corporation No. 274 c/o General Property Management Inc.",
            "Address of Owner": "242 Applewood Crescent, Unit No. 5, Concord, ON L4K 4E5",
            "Name of Contractor": "Brook Restoration",
            "Address of Contractor": "11 Kelfield Street, Toronto, ON M9W 5A1",
            "Consultant": "Davroc & Associates Ltd.",
            "Consultant Address": "2051 Williams Parkway, Unit 21, Brampton, ON L6S 5T4",
            "Publicaton Date": "2009-12-18",
            "Address": "75 Graydon Hall Dr. ",
            "Location": "City of Toronto",
            "Project": "Balcony Rehabilitation and Railing Repairs",
            "Certificate Number": "108F0DAB-8845-4CE1-A466-DCD16755C448"
        },
        {
            "Substantially Performed": "2009-11-30",
            "Date certificate signed:": "2009-12-10",
            "Name of Owner": "The Corporation of the City of St. Catharines",
            "Address of Owner": "P.O. Box 3012, 50 Church Street, St. Catharines, ON L2R 7C2",
            "Name of Contractor": "Brook Restoration Ltd.",
            "Address of Contractor": "11 Kelfield Street, Toronto, ON M9W 5A1",
            "Consultant": "Read Jones Christoffersen Ltd.",
            "Consultant Address": "500-144 Front Street West, Toronto, ON M5J 2L7",
            "Publicaton Date": "2009-12-17",
            "Address": "Carlisle St. Parking Garage 2008 Slab and Beam Shoring City Project #P08-169 ",
            "Location": "City of St. Catharines",
            "Project": "Carlisle St. Parking Garage - 2008 Slab and Beam Shoring, Option No. 2- Rental of Shoring System, City Project #P08-169",
            "Certificate Number": "73F1AFEA-B0B5-4C4C-AA0C-2A99C19858CF"
        },
        {
            "Substantially Performed": "2009-12-04",
            "Date certificate signed:": "2009-12-10",
            "Name of Owner": "Salamat Investments Corporation c/o Barney River Investments Ltd.",
            "Address of Owner": "4576 Yonge Street, Suite 300, Toronto, ON M5H 3C6",
            "Name of Contractor": "Brook Restoration Ltd.",
            "Address of Contractor": "11 Kelfield Street, Toronto, ON M9W 5A1",
            "Consultant": "Davroc & Associates Ltd.",
            "Consultant Address": "2051 Williams Parkway, Unit 21, Brampton, ON L6S 5T4",
            "Publicaton Date": "2009-12-17",
            "Address": "570 Birchmount Rd, ",
            "Location": "City of Toronto",
            "Project": "Roof Slab Rehabilitation Waterproofing and Concrete Repairs",
            "Certificate Number": "EEC0E793-07C4-4448-92B4-FA75BB946D4E"
        },
        {
            "Substantially Performed": "2009-11-06",
            "Date certificate signed:": "2009-11-10",
            "Name of Owner": "Sunrise Suites Holdings Inc. and 1522950 Ontario Inc. c/o Greenwin Property Management Ltd.",
            "Address of Owner": "1 Valleybrook Drive, Suite 200, North York, ON M3B 2S7",
            "Name of Contractor": "Brook Restoration",
            "Address of Contractor": "11 Kelfield Street, Toronto, ON M9W 5A1",
            "Consultant": "Davroc & Associates Ltd.",
            "Consultant Address": "2051 Williams Parkway, Unit 21, Brampton, ON L6S 5T4",
            "Publicaton Date": "2009-12-16",
            "Address": " ",
            "Location": "1240 Donald Street, Ottawa, ON",
            "Project": "Parking Structure Rehabilitation and Shoring",
            "Certificate Number": "9E5317A2-75E6-4818-93F5-D91DB02F6939"
        },
        {
            "Substantially Performed": "2009-11-24",
            "Date certificate signed:": "2009-11-25",
            "Name of Owner": "Redcliff Realty Management Inc. as Managers for the Owners",
            "Address of Owner": "40 University Avenue, Toronto, ON M5J 1T1",
            "Name of Contractor": "Brook Restoration Ltd.",
            "Address of Contractor": "11 Kelfield Street, Toronto, ON M9W 5A1",
            "Consultant": "N. Grgas Engineering Inc.",
            "Consultant Address": "8 Cambria Place, King City, ON L7B 1B9",
            "Publicaton Date": "2009-12-01",
            "Address": "5343+5353 Dundas Street West, Toronto ",
            "Location": "City of Toronto",
            "Project": "Parking Garage Repairs",
            "Certificate Number": "ABDD6005-92E1-4705-BB4F-54C1FDB021EB"
        },
        {
            "Substantially Performed": "2009-10-30",
            "Date certificate signed:": "2009-11-16",
            "Name of Owner": "Durham Condominium Corporation No. 125",
            "Address of Owner": "45 Cumberland Lane, Ajax, ON",
            "Name of Contractor": "Brook Restoration Ltd.",
            "Address of Contractor": "11 Kelfield Street, Toronto, ON M9W 4A1",
            "Consultant": "Enerplan Building Consultants (a division of Synergon Incorporated)",
            "Consultant Address": "69 Judson Street, Toronto, ON M8Z 1A4",
            "Publicaton Date": "2009-11-23",
            "Address": " ",
            "Location": "45 Cumberland Lane",
            "Project": "Building Envelope Remedial Work",
            "Certificate Number": "D1F999A6-E44D-4581-B3A7-BB4B0CFEE383"
        },
        {
            "Substantially Performed": "2009-07-31",
            "Date certificate signed:": "2009-10-06",
            "Name of Owner": "Toronto Catholic District School Board",
            "Address of Owner": "80 Sheppard Avenue East, Toronto, ON M2N 6E8",
            "Name of Contractor": "Brook Restoration",
            "Address of Contractor": "11 Kelfield Street, Toronto, ON M9W 5A1",
            "Consultant": "N. Grgas Engineering Inc.",
            "Consultant Address": "8 Cambria Place, King City, ON L7B 1B9",
            "Publicaton Date": "2009-10-28",
            "Address": "St. Matthew Catholic School, 18 Lavender Road, Toronto,  ON ",
            "Location": "City of Toronto",
            "Project": "Masonry Repairs",
            "Certificate Number": "4985CB1E-7491-4760-ACC0-8E13941E688D"
        },
        {
            "Substantially Performed": "2009-09-17",
            "Date certificate signed:": "2009-10-16",
            "Name of Owner": "Sun Life Insurance Company Canada, Patria Properties Inc., GP Co 13 Inc.",
            "Address of Owner": "4 Robert Speck Parkway, Mississauga, ON L4Z 1S1",
            "Name of Contractor": "Brook Restoration Ltd.",
            "Address of Contractor": "11 Kelfield Street, Toronto, ON M9W 5A1",
            "Consultant": "Yolles Partnership Inc. o/a Halcrow Yolles",
            "Consultant Address": "207 Queen's Quay West, Suite 550, Toronto, ON M5J 1A7",
            "Publicaton Date": "2009-10-27",
            "Address": "1 and 3 Robert Speck Parkway, Mississauga, ON ",
            "Location": "City of Mississauga",
            "Project": "Mississauga Executive Centre 1 & 3 - 2009 Parking Garage Repairs",
            "Certificate Number": "2716FFB8-BD7B-48C1-86AB-F6835BD0855B"
        },
        {
            "Substantially Performed": "2009-08-13",
            "Date certificate signed:": "2009-08-19",
            "Name of Owner": "York Condominium Corporation No. 170",
            "Address of Owner": "270 Timberbank Blvd., Toronto, ON",
            "Name of Contractor": "Brook Restoration Ltd.",
            "Address of Contractor": "11 Kelfield Street, Toronto, ON M9W 5A1",
            "Consultant": "Building Sciences Inc.",
            "Consultant Address": "221 Rayette Road, Unit 1, Concord, ON L4K 2G1",
            "Publicaton Date": "2009-10-23",
            "Address": " ",
            "Location": "270 Timberbank Blvd., Toronto",
            "Project": "2009 Parking Garage Repairs",
            "Certificate Number": "181B4520-BC39-481C-BFCB-2FE6014B77C1"
        },
        {
            "Substantially Performed": "2009-10-19",
            "Date certificate signed:": "2009-10-19",
            "Name of Owner": "CityHousing Hamilton - Capital Works Department",
            "Address of Owner": "55 Hess Street South, 23rd Floor, PO Box 2500, Hamilton, ON",
            "Name of Contractor": "Brook Restoration",
            "Address of Contractor": "11 Kelfield Street, Toronto, ON M9W 5A1",
            "Consultant": "Peto MacCallum Ltd.",
            "Consultant Address": "45 Burford Road, Hamilton, ON L8E 3C6",
            "Publicaton Date": "2009-10-23",
            "Address": " ",
            "Location": "226 Rebecca Street, Hamilton, ON",
            "Project": "Exterior Insulation and Finish System (EIFS) Cladding Installation under Peto MacCallum Ltd. Specification No. 09HE005",
            "Certificate Number": "34557923-C315-4192-BDDD-FF43026428E6"
        },
        {
            "Substantially Performed": "2009-09-30",
            "Date certificate signed:": "2009-10-06",
            "Name of Owner": "Inter Faith Homes c/o DMS Properties",
            "Address of Owner": "231 Bloor Street, Oshawa, ON",
            "Name of Contractor": "Brook Restoration",
            "Address of Contractor": "11 Kelfield Street, Toronto,ON M9W 5A1",
            "Consultant": "Enerplan Building Consultants (a division of Synergon Incorporated)",
            "Consultant Address": "69 Judson Street, Toronto, ON M8Z 1A4",
            "Publicaton Date": "2009-10-13",
            "Address": "231 Bloor Street ",
            "Location": "Oshawa, ON",
            "Project": "Building Envelope Remedial Work",
            "Certificate Number": "79013E58-E5CC-4F32-901B-CDC7909FD336"
        },
        {
            "Substantially Performed": "2009-09-25",
            "Date certificate signed:": "2009-10-02",
            "Name of Owner": "Halton Condominium Corporation No. 177",
            "Address of Owner": "1901, 1093 & 1905 Pilgrims Way, Oakville, ON L6M 2X1",
            "Name of Contractor": "Brook Restoration Limited",
            "Address of Contractor": "11 Kelfield Street, Toronto, ON M9W 5A1",
            "Consultant": "Kleinfeldt Consultants Limited",
            "Consultant Address": "2400 Meadowpine Blvd., Suite 102, Mississauga, ON L5N 6S2",
            "Publicaton Date": "2009-10-08",
            "Address": "1901, 1903 and 1905 Pilgrims Ways, Oakville,  ON ",
            "Location": "Town of Oakville",
            "Project": "Balcony Slab Rehabilitation and Various Repairs",
            "Certificate Number": "EF4CD31B-6ADF-403D-9561-6DE849FD3724"
        },
        {
            "Substantially Performed": "2009-09-21",
            "Date certificate signed:": "2009-09-24",
            "Name of Owner": "The Independent Order of Foresters c/o Redcliff Realty Management Inc.",
            "Address of Owner": "789 Don Mills Road, Suite 210, Toronto, ON M3C 1T5",
            "Name of Contractor": "Brook Restoration Ltd.",
            "Address of Contractor": "11 Kelfield Street, Toronto, ON M9W 5A1",
            "Consultant": "N. Grgas Engineering Inc.",
            "Consultant Address": "8 Cambria Place, King City, ON L7B 1B9",
            "Publicaton Date": "2009-10-01",
            "Address": "789 Don Mills Road ",
            "Location": "City of Toronto",
            "Project": "Parking Garage Repairs",
            "Certificate Number": "06AC6150-0C53-4CA0-92A0-1CD096B21099"
        },
        {
            "Substantially Performed": "2009-09-15",
            "Date certificate signed:": "2009-09-23",
            "Name of Owner": "SNC Lavalin ProFac",
            "Address of Owner": "2 Gibbs Road, Etobicoke, ON M9B 6L6",
            "Name of Contractor": "Brook Restoration",
            "Address of Contractor": "11 Kelfield Street, Toronto, ON M9W 5A1",
            "Consultant": "Bortolotto Design Architect Inc.",
            "Consultant Address": "533 College Street, Suite 401, Toronto, ON M6G 1A8",
            "Publicaton Date": "2009-10-01",
            "Address": "1 Front Street West, Toronto, ON ",
            "Location": "City of Toronto",
            "Project": "Painting of Walls of 4th, 5th and 6th Floor at Public Corridors, Elevator Lobby and Stairs",
            "Certificate Number": "AE9F40BD-70DC-4E3C-BB82-88096036BF9D"
        }
    ]
}